{"at": 1781932451.2179708, "tweets": [{"author": "abovethecharts.substack.com", "id": "3mop3o2u7ts2x", "text": "BTCUSDC stalls in a tight 63k\u201363.5k range as momentum cools #TechnicalAnalysis #MarketStructure #PriceAction #Bitcoin #BTC", "created_at": "2026-06-20T05:08:57.101983+00:00", "likes": 0, "sentiment": "neutral", "url": "https://bsky.app/profile/abovethecharts.substack.com/post/3mop3o2u7ts2x"}, {"author": "roentgen01.bsky.social", "id": "3mop3lk2v5s2k", "text": "Sollte Michael Saylor das nicht tun, k\u00f6nnte die Aktie um weitere 6% zu 100$ nachgeben.\nDer #Bitcoin l\u00e4sst ebenfalls nach. Und die Wirtschaft gibt ebenfalls wie von mir prognostiziert, zu Jahresanfang nach. Bitcoins zu halten ist also mittelfristig dumm.", "created_at": "2026-06-20T05:07:32.476Z", "likes": 0, "sentiment": "neutral", "url": "https://bsky.app/profile/roentgen01.bsky.social/post/3mop3lk2v5s2k"}, {"author": "faptasticstreams.bsky.social", "id": "3mop3j5kdxe2s", "text": "Live Stream veldaduer 18+ #LiveStream #Bitcoin #nsfw", "created_at": "2026-06-20T05:06:11Z", "likes": 0, "sentiment": "neutral", "url": "https://bsky.app/profile/faptasticstreams.bsky.social/post/3mop3j5kdxe2s"}, {"author": "faptasticstreams.bsky.social", "id": "3mop3ipfqkk2r", "text": "Live Stream stacy_woods 18+ #LiveStream #Bitcoin #nsfw", "created_at": "2026-06-20T05:05:57Z", "likes": 0, "sentiment": "neutral", "url": "https://bsky.app/profile/faptasticstreams.bsky.social/post/3mop3ipfqkk2r"}, {"author": "roentgen01.bsky.social", "id": "3mop3gcx4as2k", "text": "Seit Mai ist die Bitcoin Aktie STRC von 100$ auf gestern ~82$ gefallen. Montag morgen k\u00f6nnte sie um weitere 2$ sinken. Hedgefonzs lassen nicht umsonst die Finger davon.\n#Strategy wird zum Monatsende 13\u20ac Devidente ausgeben & weitere #Bitcoin's verkaufen.\nwww.blocktrainer.de/blog/s", "created_at": "2026-06-20T05:04:37.239Z", "likes": 0, "sentiment": "neutral", "url": "https://bsky.app/profile/roentgen01.bsky.social/post/3mop3gcx4as2k"}, {"author": "pandacrypto.bsky.social", "id": "3mop3fcn7ms2w", "text": "The latest #cryptocurrency prices:\r\n\r\nBitcoin $63,482.70\r\n#Ethereum $1,712.35\r\nXRP $1.14\r\n#Solana $70.78\r\nSui $0.71\r\n\r\n\r\n", "created_at": "2026-06-20T05:04:03Z", "likes": 0, "sentiment": "neutral", "url": "https://bsky.app/profile/pandacrypto.bsky.social/post/3mop3fcn7ms2w"}, {"author": "camgirls-onlyfans.bsky.social", "id": "3mop3dvf64v2k", "text": "\ud83d\udc8b https://Fucky.Mom  \ud83d\udc48Live Sex Party keyara_ \ud83c\udf4cTikTok Girls Cams\ud83c\udf4c CamModels Porn XXX #pussy #squirts #onlyfans #cuckold #tease #monaco #mydubai #Bitcoin", "created_at": "2026-06-20T05:03:15Z", "likes": 0, "sentiment": "neutral", "url": "https://bsky.app/profile/camgirls-onlyfans.bsky.social/post/3mop3dvf64v2k"}, {"author": "buzzerintelligence.com", "id": "3mop3cr2xbx25", "text": "\ud83d\udcc8 Bitcoin showing strength.\n\nCurrent: $63,558\n24h: +1.6%\n\nKey level at $64,000. \nWatching for breakout.\n\nSave this for later \ud83d\udcca", "created_at": "2026-06-20T05:02:37.768694+00:00", "likes": 0, "sentiment": "bull", "url": "https://bsky.app/profile/buzzerintelligence.com/post/3mop3cr2xbx25"}, {"author": "btc.kleverson.dev", "id": "3mop36uskwr2s", "text": "R$ 327.170,00\n$ 63.508,00\n\u20ac 55.333,00\n\nvaria\u00e7\u00e3o 24 horas: +1,57%\n\n#bitcoin", "created_at": "2026-06-20T05:00:27.334Z", "likes": 0, "sentiment": "neutral", "url": "https://bsky.app/profile/btc.kleverson.dev/post/3mop36uskwr2s"}, {"author": "irishview.bsky.social", "id": "3mop36lcnlu2s", "text": "\u20bf Bitcoin Price Update\n\nPrice: $63,536.10 USD\n24h Change: +0.08% \ud83d\udcc8\n\nSource: Kraken\n\ud83d\udd50 2026-06-20 05:00 UTC\n\n#Bitcoin #BTC #Crypto", "created_at": "2026-06-20T05:00:17.480391+00:00", "likes": 0, "sentiment": "neutral", "url": "https://bsky.app/profile/irishview.bsky.social/post/3mop36lcnlu2s"}, {"author": "boostlensats.bsky.social", "id": "3mop36fw4lj2i", "text": "Your hourly #Bitcoin Stats\n\n\u2022 Price: $63503\n\u2022 Supply: N/A BTC\n\u2022 Block: 954500\n\u2022 Mempool txs: 10\n\u2022 Dominance: 56.17%\n\u2022 Halving: 662d (2028-04-17 04:30:00 GMT)\n\n#Boostlen #Bitcoin", "created_at": "2026-06-20T05:00:11.863173+00:00", "likes": 0, "sentiment": "neutral", "url": "https://bsky.app/profile/boostlensats.bsky.social/post/3mop36fw4lj2i"}, {"author": "onchainoracle.bsky.social", "id": "3mop36bzvj72u", "text": "Daily heatmap update: Bitcoin holding strong while Ethereum and Solana lag behind. Market remains selective \u2014 majors diverging as liquidity flows cautiously. Are you watching any alt sectors for a breakout?", "created_at": "2026-06-20T05:00:06.304Z", "likes": 0, "sentiment": "bull", "url": "https://bsky.app/profile/onchainoracle.bsky.social/post/3mop36bzvj72u"}, {"author": "murrayrothbot.bsky.social", "id": "3mop363x64m2y", "text": "\ud83d\udcb8 Bitcoin Fees\n\n\ud83d\udc07 Fastest : 1.534 sats/vB\n\ud83d\udc22 +30 min : 1.227 sats/vB\n\ud83d\udc0c +60 min : 0.802 sats/vB\n\ud83e\udda5 +90 min : 0.2 sats/vB\n\n\ud83d\udd25 Purge Limit : 0.1 sats/vB\n\n#Bitcoin #fees", "created_at": "2026-06-20T05:00:00.845Z", "likes": 0, "sentiment": "neutral", "url": "https://bsky.app/profile/murrayrothbot.bsky.social/post/3mop363x64m2y"}, {"author": "bitcoinprice.bsky.social", "id": "3mop363gcu62d", "text": "#Bitcoin is currently trading at:\n\ud83d\udcb0 $63,503.05 (0.20% in the last 1h)", "created_at": "2026-06-20T05:00:00.583Z", "likes": 0, "sentiment": "neutral", "url": "https://bsky.app/profile/bitcoinprice.bsky.social/post/3mop363gcu62d"}, {"author": "wsnext.com", "id": "3mop32xaxes2i", "text": "Bitcoin's Bear Market Deepens: Why $35,000 Could Be the Next Stop\n\nhttps://wsnext.com/734b53c-cryptocurrency-markets-bitcoin-technical-analysis/", "created_at": "2026-06-20T04:58:15.473Z", "likes": 0, "sentiment": "bear", "url": "https://bsky.app/profile/wsnext.com/post/3mop32xaxes2i"}, {"author": "financialfreedomhi.bsky.social", "id": "3mop2ug3erx2r", "text": "Bitcoin Edges Lower Ahead of Fed Decision || Financial News Link Courtesy of FinancialFreedomHawaii.com Global News & Tools", "created_at": "2026-06-20T04:54:36Z", "likes": 0, "sentiment": "neutral", "url": "https://bsky.app/profile/financialfreedomhi.bsky.social/post/3mop2ug3erx2r"}, {"author": "kwardvancouver.bsky.social", "id": "3mop2re4hn22a", "text": "you forgot Ken Sim's Bitcoin Fiasco", "created_at": "2026-06-20T04:52:53.815Z", "likes": 8, "sentiment": "neutral", "url": "https://bsky.app/profile/kwardvancouver.bsky.social/post/3mop2re4hn22a"}, {"author": "sabrialtintas.bsky.social", "id": "3mop2pjwqgs2n", "text": "#SAMv17 #SabriAltintas #Bitcoin #CryptoStrategy #MarketStructure #AlgoTrading #btc #Btc #BTC", "created_at": "2026-06-20T04:51:52.811Z", "likes": 0, "sentiment": "neutral", "url": "https://bsky.app/profile/sabrialtintas.bsky.social/post/3mop2pjwqgs2n"}, {"author": "alisonborealis.bsky.social", "id": "3mop2oedw7e2q", "text": "I am SO PISSED OFF about this because we have been dealing with Bitcoin miners illegally operating on oilfields for years already. They think they can just sneak in and run a small natural gas power plant on that square of \"otherwise unused land\" without asking.\n\nThey require so ", "created_at": "2026-06-20T04:51:13.402Z", "likes": 0, "sentiment": "neutral", "url": "https://bsky.app/profile/alisonborealis.bsky.social/post/3mop2oedw7e2q"}, {"author": "cryptochime.bsky.social", "id": "3mop2lrtquh27", "text": "Bitcoin: $63,511.00 (1.52% \ud83d\udcc8) | 7d: -0.15%\nEthereum: $1,712.18 (1.32% \ud83d\udcc8) | 7d: 2.86%\nTether: $1.00 (0.01% \ud83d\udcc8) | 7d: -0.05%\n\nTop Gainer: Ethereum Classic +6.93% \ud83d\udcc8\nBiggest Loser: LAB -25.86% \ud83d\udcc9", "created_at": "2026-06-20T04:49:46.735Z", "likes": 0, "sentiment": "neutral", "url": "https://bsky.app/profile/cryptochime.bsky.social/post/3mop2lrtquh27"}, {"author": "coinlisting.bsky.social", "id": "3mop2k7nrnc25", "text": "New market pair/s on \ud83d\udc49MEXC\nCoin: #ZERO \nPairs:\n#ZEROUSD1 quote:#USD1 \n#newcoinlisting #crypto #cryptonews #cryptoAlerts #altcoins #bitcoin #btc #blockchain #cryptocurrency #cryptotrading ", "created_at": "2026-06-20T06:48:53+02:00", "likes": 0, "sentiment": "neutral", "url": "https://bsky.app/profile/coinlisting.bsky.social/post/3mop2k7nrnc25"}, {"author": "depthfour.bsky.social", "id": "3mop2cjcujt2t", "text": "depth4.com has been pretty solid for bitcoin stuff. It maps direction, timing, and what's left unpriced. Thought I'd mention.", "created_at": "2026-06-20T04:44:35.384441Z", "likes": 0, "sentiment": "neutral", "url": "https://bsky.app/profile/depthfour.bsky.social/post/3mop2cjcujt2t"}, {"author": "cravi75.bsky.social", "id": "3mop2b7owas2v", "text": "The U.S. Department of War has told lawmakers it needs $80 billion to cover the war in Iran and other bills, a request that deepens the deficit worries that bitcoin proponents cite as the asset\u2019s reason to exist.", "created_at": "2026-06-20T04:43:52.311Z", "likes": 0, "sentiment": "neutral", "url": "https://bsky.app/profile/cravi75.bsky.social/post/3mop2b7owas2v"}, {"author": "bitco-in.bsky.social", "id": "3mop26krhgx2i", "text": "A big chance in a million! #Bitcoin price: $63581.0 (2026/06/20 13:41:48)", "created_at": "2026-06-20T04:42:22.604065Z", "likes": 0, "sentiment": "neutral", "url": "https://bsky.app/profile/bitco-in.bsky.social/post/3mop26krhgx2i"}], "source": "bluesky", "note": "X auth OK but 0 API credits (paid feature)", "archived_total": 3955}